[{"date": "22 Juil 2022", "titre": "Graphiste", "societe": "COREALI", "contrat": "CDD", "description": [{"s_titre": "activit\u00e9 de l'entreprise", "s_description": "\r\n                Agence de communication \u00e9v\u00e9nementielle bas\u00e9e \u00e0 Tana.\nOrganisation d\u2019\u00e9v\u00e9nements d\u2019entreprise/ institutionnel cl\u00e9s en main, communication \u00e9v\u00e9nementielle, design d\u2019espace \u00e9v\u00e9nementiel \nNos valeurs : excellence, passion, int\u00e9grit\u00e9, cr\u00e9ativit\u00e9, professionnalisme"}, {"s_titre": "Missions", "s_description": "\r\n                \r\n                Bonne compr\u00e9hension des besoins du client\nConception de supports visuels (pour support de communication, design d\u2019espace, mise en page de livres) correspondant au brief client\nRespect des d\u00e9lais et priorisation des t\u00e2ches \nBonne ma\u00eetrise des logiciels de la suite Adobe et logiciel 3D Blender"}, {"s_titre": "Profil", "s_description": "\n\nCr\u00e9atif\nCurieux\nDynamique\nForce de proposition \nPassionn\u00e9 par les arts graphiques"}], "url": "https://www.portaljob-madagascar.com/emploi/view/coreali51-graphiste107467", "category": "informatique-web"}]